upt_debian/__init__.py
upt_debian/upt_debian.py
upt_debian/templates/changelog
upt_debian/templates/compat
upt_debian/templates/control
upt_debian/templates/control.python
upt_debian/templates/copyright
upt_debian/templates/copyright.python
upt_debian/templates/rules
upt_debian/templates/rules.python
upt_debian/templates/watch
upt_debian/templates/watch.python
upt_debian/templates/source/format
upt_debian/tests/__init__.py
upt_debian/tests/test_debian_backend.py
upt_debian/tests/test_debian_package.py
upt_debian/tests/test_python_package.py
upt_debian-0.1.1.dist-info/LICENSE
upt_debian-0.1.1.dist-info/METADATA
upt_debian-0.1.1.dist-info/WHEEL
upt_debian-0.1.1.dist-info/entry_points.txt
upt_debian-0.1.1.dist-info/top_level.txt
upt_debian-0.1.1.dist-info/RECORD
